{"@context":"https://iiif.io/api/presentation/3/context.json","id":"https://mathewjordan.github.io/homer/api/facet/date/1882.json","type":"Collection","label":{"none":["1882"]},"items":[{"id":"https://iiif.harvardartmuseums.org/manifests/object/307768","type":"Manifest","label":{"none":["The Lookout"]},"thumbnail":[{"id":"https://ids.lib.harvard.edu/ids/iiif/17817032/full/!170,170/0/default.jpg","type":"Image","service":[{"@id":"https://ids.lib.harvard.edu/ids/iiif/17817032","@type":"ImageService2","profile":"level2"}]}],"homepage":[{"id":"https://mathewjordan.github.io/homer/works/the-lookout","type":"Text","label":{"none":["The Lookout"]}}]}],"partOf":[{"id":"https://mathewjordan.github.io/homer/api/facet/date.json","type":"Collection"}],"summary":{"none":["Date"]},"homepage":[{"id":"https://mathewjordan.github.io/homer/search?date=1882","type":"Text","label":{"none":["1882"]}}]}